thingamon/__init__.py
thingamon/client.py
thingamon/thing.py
thingamon-1.0.0.dist-info/LICENSE
thingamon-1.0.0.dist-info/METADATA
thingamon-1.0.0.dist-info/WHEEL
thingamon-1.0.0.dist-info/top_level.txt
thingamon-1.0.0.dist-info/RECORD
