Metadata-Version: 2.1
Name: thingamon
Version: 1.0.0
Summary: AWS MQTT IoT Thing monitor
Home-page: https://github.com/mgk/thingamon/blob/master/README.md
Author: Michael Keirnan
Author-email: michael@keirnan.com
License: MIT
Keywords: aws iot mqtt sensor
Platform: any
Classifier: Development Status :: 3 - Alpha
Classifier: Intended Audience :: Developers
Classifier: Intended Audience :: Science/Research
Classifier: Environment :: Console
Classifier: License :: OSI Approved :: MIT License
Classifier: Natural Language :: English
Classifier: Topic :: Home Automation
Classifier: Topic :: Internet
Classifier: Topic :: Software Development :: Libraries :: Python Modules
Classifier: Topic :: Scientific/Engineering
Classifier: Programming Language :: Python
Classifier: Programming Language :: Python :: 2
Classifier: Programming Language :: Python :: 2.7
Classifier: Programming Language :: Python :: 3
Classifier: Programming Language :: Python :: 3.4
Classifier: Programming Language :: Python :: 3.5
Requires-Dist: paho-mqtt
Requires-Dist: certifi
